prefect_cloud_manager/__init__.py
prefect_cloud_manager/prefect_account.py
prefect_cloud_manager-0.1.1.dist-info/LICENSE
prefect_cloud_manager-0.1.1.dist-info/METADATA
prefect_cloud_manager-0.1.1.dist-info/WHEEL
prefect_cloud_manager-0.1.1.dist-info/entry_points.txt
prefect_cloud_manager-0.1.1.dist-info/top_level.txt
prefect_cloud_manager-0.1.1.dist-info/RECORD
