Metadata-Version: 2.1
Name: prefect-cloud-manager
Version: 0.1.1
Summary: A convenient CLI for managing multiple Prefect accounts.
Home-page: https://github.com/ngriffiths13/prefect-cloud-manager
Author: Nelson Griffiths
Author-email: nelsongriffiths123@gmail.com
License: MIT
Platform: UNKNOWN
Classifier: License :: OSI Approved :: MIT License
Classifier: Programming Language :: Python :: 3
Classifier: Programming Language :: Python :: 3.8
Requires-Dist: fire
Requires-Dist: pyyaml
Requires-Dist: toml
